{
    "order_id": {
        "S": "O1001"
    },
    "customer_id": {
        "S": "C002"
    },
    "order_date": {
        "S": "2024-06-15T10:30:00Z"
    },
    "order_status": {
        "S": "Processing"
    },
    "total_amount": {
        "N": "699.99"
    },
    "products": {
        "L": [
            {
                "M": {
                    "product_id": {
                        "S": "P002"
                    },
                    "quantity": {
                        "N": "1"
                    },
                    "price": {
                        "N": "699.99"
                    }
                }
            }
        ]
    }
}